[
  {
    "Namespace": "",
    "Key": "389248444522A57DA5866190F07441E1",
    "Hash": 3808886888,
    "SourceString": "Spring",
    "LocalizedString": ""
  },
  {
    "Namespace": "",
    "Key": "01858646448C0CEFF388C4899C5727E1",
    "Hash": 2582317399,
    "SourceString": "Summer",
    "LocalizedString": ""
  },
  {
    "Namespace": "",
    "Key": "89D447504F0490DE19395594E07C4300",
    "Hash": 3352945333,
    "SourceString": "Autumn",
    "LocalizedString": ""
  },
  {
    "Namespace": "",
    "Key": "F5E4290D4CD42D6712519B87A1514DD3",
    "Hash": 2070176345,
    "SourceString": "Winter",
    "LocalizedString": ""
  }
]